deepblu/__init__.py
deepblu/di/__init__.py
deepblu-0.1.0.dist-info/METADATA
deepblu-0.1.0.dist-info/WHEEL
deepblu-0.1.0.dist-info/RECORD
