Metadata-Version: 2.1
Name: deepblu
Version: 0.1.0
Summary: Library for advanced architectures/patterns in modern Python. Domain-Driven Design (DDD), CQRS, Event Sourcing, Event-driven architectures, message queues, unit of work dependency injection and more.
License: MIT
Author: Carlo Casorzo
Author-email: carlo@deepblu.dev
Requires-Python: >=3.11,<4.0
Classifier: License :: OSI Approved :: MIT License
Classifier: Programming Language :: Python :: 3
Classifier: Programming Language :: Python :: 3.11
